djangocms_partners/__init__.py
djangocms_partners/admin.py
djangocms_partners/apps.py
djangocms_partners/models.py
djangocms_partners/tests.py
djangocms_partners/views.py
djangocms_partners/locale/fr/LC_MESSAGES/django.mo
djangocms_partners/locale/fr/LC_MESSAGES/django.po
djangocms_partners/migrations/0001_initial.py
djangocms_partners/migrations/0002_auto_20180807_1400.py
djangocms_partners/migrations/__init__.py
djangocms_partners/templatetags/__init__.py
djangocms_partners/templatetags/cms_partners_tags.py
djangocms_partners-0.5.dist-info/METADATA
djangocms_partners-0.5.dist-info/RECORD
djangocms_partners-0.5.dist-info/WHEEL
djangocms_partners-0.5.dist-info/top_level.txt
